MANIFEST.in
requirements.txt
setup.py
deep_genomics/__init__.py
deep_genomics/neural.py
deep_genomics/utils.py
deep_genomics.egg-info/PKG-INFO
deep_genomics.egg-info/SOURCES.txt
deep_genomics.egg-info/dependency_links.txt
deep_genomics.egg-info/requires.txt
deep_genomics.egg-info/top_level.txt