Metadata-Version: 2.4
Name: deep_genomics
Version: 2025.8.15
Summary: Deep learning utilities for genomics
Home-page: https://github.com/jolespin/deep-genomics
Author: Josh L. Espinoza
Author-email: jol.espinoz@gmail.com
License: MIT
Requires-Dist: biom-format
Requires-Dist: pandas
Requires-Dist: ipython
Requires-Dist: ipykernel
Requires-Dist: pyarrow
Requires-Dist: anndata
Requires-Dist: tqdm
Requires-Dist: pyfastx
Requires-Dist: scikit-learn
Requires-Dist: matplotlib
Requires-Dist: loguru
Requires-Dist: skclust>=2025.8.5
Requires-Dist: numpy<2.0.0
Requires-Dist: nbformat
Dynamic: author
Dynamic: author-email
Dynamic: home-page
Dynamic: license
Dynamic: requires-dist
Dynamic: summary
